README.md
setup.cfg
setup.py
payjs/__init__.py
payjs/base.py
payjs/example.py
payjs/exceptions.py
payjs/notify.py
payjs/result.py
payjs/sign.py
payjs/test.py
payjs/utils.py
payjs.egg-info/PKG-INFO
payjs.egg-info/SOURCES.txt
payjs.egg-info/dependency_links.txt
payjs.egg-info/requires.txt
payjs.egg-info/top_level.txt