Metadata-Version: 1.1
Name: payjs
Version: 1.2.4
Summary: An interface for payjs.cn
Home-page: https://github.com/ImSingee/PayJS
Author: Brian Wang
Author-email: imsingee@gmail.com
License: MIT
Download-URL: https://github.com/ImSingee/PayJS/archive/v1.2.4.tar.gz
Keywords: python package payjs interface API wechat pay
Platform: UNKNOWN
Classifier: Programming Language :: Python :: 3.6
